Metadata-Version: 2.1
Name: django-context-extra-view
Version: 2020.7.1
Summary: context extra data
Home-page: https://github.com/andrewp-as-is/django-context-extra-view.py
License: Unlicense
Keywords: django view context
Platform: UNKNOWN
Classifier: Framework :: Django
Classifier: License :: Public Domain
Classifier: Operating System :: OS Independent
Classifier: Programming Language :: Python :: 3
